a2km/__init__.py
a2km/__main__.py
a2km/_api.py
a2km/_cli.py
a2km/operations.py
a2km-0.2.1.dist-info/LICENSE
a2km-0.2.1.dist-info/METADATA
a2km-0.2.1.dist-info/WHEEL
a2km-0.2.1.dist-info/entry_points.txt
a2km-0.2.1.dist-info/top_level.txt
a2km-0.2.1.dist-info/RECORD
