Metadata-Version: 2.2
Name: a2km
Version: 0.2.1
Summary: Assistent to the (Jupyter) Kernel Manager
Author-email: Min RK <benjaminrk@gmail.com>
License: BSD-3-Clause
Project-URL: Homepage, https://github.com/minrk/a2km
Project-URL: Source, https://github.com/minrk/a2km
Project-URL: Tracker, https://github.com/minrk/a2km/issues
Keywords: Jupyter
Classifier: Development Status :: 1 - Planning
Classifier: Intended Audience :: Developers
Classifier: Intended Audience :: System Administrators
Classifier: Intended Audience :: Science/Research
Classifier: Programming Language :: Python
Classifier: Programming Language :: Python :: 3
Classifier: Framework :: Jupyter
Requires-Python: >=3.9
License-File: LICENSE
Requires-Dist: jupyter-core
Provides-Extra: test
Requires-Dist: pytest; extra == "test"
Requires-Dist: pytest-cov; extra == "test"
Requires-Dist: jupyter_client; extra == "test"
